main.py
actions/__init__.py
actions/help/__init__.py
actions/help/help.py
actions/init/__init__.py
actions/init/config.py
actions/init/initialization.py
actions/looker/__init__.py
actions/looker/bigquery_client.py
actions/looker/config_loader.py
actions/looker/field_utils.py
actions/looker/generate.py
actions/looker/lookml_base_dict.py
actions/looker/lookml_generator.py
actions/looker/lookml_measure_module.py
actions/looker/lookml_module.py
actions/models/__init__.py
actions/models/config.py
actions/models/lookml.py
actions/models/metadata.py
actions/utils/__init__.py
actions/utils/config_docs.py
actions/utils/config_validator.py
actions/utils/safe_print.py
concordia_cli-0.2.0.dist-info/METADATA
concordia_cli-0.2.0.dist-info/WHEEL
concordia_cli-0.2.0.dist-info/entry_points.txt
concordia_cli-0.2.0.dist-info/top_level.txt
concordia_cli-0.2.0.dist-info/RECORD
