Metadata-Version: 2.4
Name: concordia-cli
Version: 0.2.0
Summary: Concordia CLI - Generate LookML from BigQuery using Looker & Dataform
Author: Cobry
License: MIT
Project-URL: Homepage, https://github.com/CobryDev/concordia-cli
Project-URL: Repository, https://github.com/CobryDev/concordia-cli
Project-URL: Bug Tracker, https://github.com/CobryDev/concordia-cli/issues
Keywords: looker,lookml,bigquery,dataform,cli,dbt
Classifier: Development Status :: 3 - Alpha
Classifier: Programming Language :: Python :: 3
Classifier: Programming Language :: Python :: 3.11
Classifier: Programming Language :: Python :: 3.12
Classifier: Programming Language :: Python :: 3.13
Classifier: License :: OSI Approved :: MIT License
Classifier: Operating System :: OS Independent
Classifier: Topic :: Database
Classifier: Topic :: Software Development :: Code Generators
Classifier: Typing :: Typed
Requires-Python: >=3.11
Requires-Dist: click
Requires-Dist: pyyaml
Requires-Dist: google-cloud-bigquery>=3.0.0
Requires-Dist: google-auth>=2.0.0
Requires-Dist: jinja2>=3.0.0
Requires-Dist: lkml>=1.3.0
Requires-Dist: pandas>=1.5.0
Requires-Dist: pandas-gbq>=0.19.0
Requires-Dist: pydantic>=2.0.0
Requires-Dist: ruamel.yaml>=0.17.0
Requires-Dist: tomli>=2.2.1
